mcp_server_git/__init__.py
mcp_server_git/__main__.py
mcp_server_git/server.py
mcp_git_airnet-0.0.3.dist-info/METADATA
mcp_git_airnet-0.0.3.dist-info/WHEEL
mcp_git_airnet-0.0.3.dist-info/entry_points.txt
mcp_git_airnet-0.0.3.dist-info/licenses/LICENSE
mcp_git_airnet-0.0.3.dist-info/RECORD
